<?xml version='1.0' encoding='UTF-8'?>
<song xmlns="http://openlyrics.info/namespace/2009/song" version="0.8" createdIn="OpenLP 3.1.1" modifiedIn="OpenLP 3.1.1" modifiedDate="2023-09-23T09:34:36">
  <properties>
    <titles>
      <title>Bemegyek a Szentek</title>
      <title>For Your Name is Holy</title>
    </titles>
    <copyright>1999 Integrity's Hosanna! Music</copyright>
    <verseOrder>v1 p1 c1</verseOrder>
    <authors>
      <author type="words">Jim Cowan</author>
      <author type="music">Jim Cowan</author>
      <author type="translation">Flach Ferenc</author>
    </authors>
    <songbooks>
      <songbook name="Szent András énekfüzet" entry="259"/>
    </songbooks>
  </properties>
  <lyrics>
    <verse name="v1">
      <lines>Bemegyek a Szentek Szentjébe,<br/>bemegyek a Bárány vérén át.<br/>Bemegyek, csak Téged dicsérlek,<br/>bemegyek, hogy hódoljak Neked.</lines>
    </verse>
    <verse name="p1">
      <lines>Uram, dicsérlek, dicsérlek,<br/>Uram, dicsérlek, dicsérlek!</lines>
    </verse>
    <verse name="c1">
      <lines>Neved áldom, szent vagy, szent vagy Uram,<br/>A Te neved áldom, szent vagy, szent vagy Uram!</lines>
    </verse>
  </lyrics>
</song>
