<?xml version='1.0' encoding='UTF-8'?>
<song xmlns="http://openlyrics.info/namespace/2009/song" version="0.8" createdIn="OpenLP 2.4.6" modifiedIn="OpenLP 2.4.6" modifiedDate="2023-10-08T08:34:24">
  <properties>
    <titles>
      <title>Isten báránya</title>
    </titles>
    <authors>
      <author>ismeretlen</author>
    </authors>
  </properties>
  <lyrics>
    <verse name="v1">
      <lines>Isten Báránya, <br/>te elveszed a <br/>világ bűneit, <br/>irgalmazz, irgalmazz nekünk!</lines>
    </verse>
    <verse name="v2">
      <lines> Isten Báránya, <br/>te elveszed a <br/>világ bűneit,<br/> irgalmazz, irgalmazz nekünk!</lines>
    </verse>
    <verse name="v3">
      <lines> Isten Báránya, <br/>te elveszed a <br/>világ bűneit, <br/>adj nekünk, adj nekünk békét!</lines>
    </verse>
  </lyrics>
</song>
