<?xml version='1.0' encoding='UTF-8'?>
<song xmlns="http://openlyrics.info/namespace/2009/song" version="0.8" createdIn="OpenLP 2.4.6" modifiedIn="OpenLP 2.4.6" modifiedDate="2024-12-31T01:45:19">
  <properties>
    <titles>
      <title>Minden új nap</title>
      <title>My Greatest Love Is You</title>
    </titles>
    <copyright>© 1997 Hillsong Music Publishing</copyright>
    <verseOrder>v1 c1</verseOrder>
    <authors>
      <author type="words">Russell Fragar</author>
      <author type="music">Russell Fragar</author>
      <author type="translation">Veress Zoltán</author>
      <author type="translation">Pintér Béla</author>
    </authors>
    <songbooks>
      <songbook name="Szent András énekfüzet" entry="189"/>
    </songbooks>
  </properties>
  <lyrics>
    <verse name="v1">
      <lines>Minden új nap <br/>Veled kezdődik el,<br/>megtöltöd szívem <br/>kincseiddel.<br/>Szentséged szépsége <br/>megújít engem.<br/>Te vagy Szerelmesem.</lines>
    </verse>
    <verse name="c1">
      <lines>Jövök Hozzád,<br/> kegyelmedbe,<br/>a folyó, mely árad,<br/> mosson meg engem!<br/>Tisztítson meg teljesen!<br/>Te vagy Szerelmesem.</lines>
    </verse>
  </lyrics>
</song>
