<?xml version='1.0' encoding='UTF-8'?>
<song xmlns="http://openlyrics.info/namespace/2009/song" version="0.8" createdIn="OpenLP 2.4.6" modifiedIn="OpenLP 2.4.6" modifiedDate="2020-12-22T14:04:12">
  <properties>
    <titles>
      <title>Jézus, boldog vagyok</title>
    </titles>
    <authors>
      <author>ismeretlen sz.</author>
    </authors>
  </properties>
  <lyrics>
    <verse name="v1">
      <lines>Jézus, <br/>csak benned bízom,<br/>nem kell más.<br/>Boldog vagyok, <br/>a Te szegényed vagyok,<br/>Veled boldog vagyok.</lines>
    </verse>
    <verse name="v2">
      <lines>Enyém az Isten országa.<br/>Boldog vagyok.</lines>
    </verse>
  </lyrics>
</song>
